{
  "learners": [
    {
      "id": "1",
      "name": "Tushar",
      "email": "tushar@tushar.com",
      "password": "tushar123",
      "phone": "9996159991",
      "pincode": "112445",
      "city": "New Delhi",
      "state": "Delhi",
      "country": "India",
      "dob": "06/25/24",
      "gender": "male",
      "coursesPurchased": [
        1,
        2
      ]
    },
    {
      "id": "2",
      "name": "Rajat",
      "email": "rajat@rajat.com",
      "password": "rajat123",
      "phone": "9996159992",
      "pincode": "123456",
      "city": "Gurugram",
      "state": "Haryana",
      "country": "India",
      "dob": "01/25/24",
      "gender": "male",
      "coursesPurchased": [
        2
      ]
    },
    {
      "id": "3",
      "name": "Naman",
      "email": "naman@naman.com",
      "password": "naman123",
      "phone": "9996159993",
      "pincode": "990876",
      "city": "Mohali",
      "state": "Punjab",
      "country": "India",
      "dob": "04/01/22",
      "gender": "male",
      "coursesPurchased": [
        2,
        3
      ]
    },
    {
      "id": "b1b5",
      "name": "Raj Kumar",
      "email": "raj@gmail.com",
      "phone": "99615991",
      "gender": "Others",
      "dob": "2008-01-06",
      "interest": [
        "Development",
        "Business"
      ],
      "country": "India",
      "state": "J&K",
      "city": "Jammu",
      "pincode": "123660",
      "password": "raj123"
    },
    {
      "id": "1f9f",
      "name": "Shubham Kumar",
      "email": "shubham@gmail.com",
      "phone": "996148880",
      "gender": "Male",
      "dob": "2024-07-03",
      "interest": [
        "Business"
      ],
      "country": "India",
      "state": "Uttarakhand",
      "city": "Almora",
      "pincode": "123556",
      "password": "shubham123"
    }
  ],
  "instructors": [
    {
      "id": "1",
      "name": "Varnika Aneja",
      "email": "varnika@varnika.com",
      "password": "varnika123",
      "phone": "9996158881",
      "gender": "female",
      "domain": [
        "Finance",
        "Psycology"
      ]
    },
    {
      "id": "2",
      "name": "Vikas Divyakirti",
      "email": "vikas@vikas.com",
      "password": "vikas123",
      "phone": "9996158891",
      "gender": "male",
      "domain": [
        "UPSC",
        "History"
      ]
    },
    {
      "id": "3",
      "name": "Rachna Ranade",
      "email": "rachna@rachna.com",
      "password": "rachna123",
      "phone": "9896158891",
      "gender": "female",
      "domain": [
        "Economy",
        "Stock Market"
      ]
    },
    {
      "id": "6e18",
      "name": "Manish Gupta",
      "email": "manish@gmail.com",
      "phone": "9908802345",
      "gender": "Male",
      "domain": [
        "Health & Fitness",
        "Personal Development"
      ],
      "password": "manish123"
    },
    {
      "id": "3679",
      "name": "Ranju Aneja",
      "email": "ranju@gmail.com",
      "phone": "9989099664",
      "gender": "Female",
      "domain": [
        "Personal Development"
      ],
      "password": "ranju123"
    }
  ],
  "courses": [
    {
      "id": "1",
      "name": "Investment Management",
      "instructor": 1,
      "domain": [
        "Finance"
      ]
    },
    {
      "id": "2",
      "name": "Journey to the Indian Past",
      "instructor": 2,
      "domain": [
        "History",
        "UPSC"
      ]
    },
    {
      "id": "3",
      "name": "UPSC: Marathon",
      "instructor": 2,
      "domain": [
        "UPSC"
      ]
    },
    {
      "id": "4",
      "name": "Lets Us Stock Market",
      "instructor": 3,
      "domain": [
        "Stock Market"
      ]
    }
  ]
}